logshot/__init__.py
logshot/logging.py
logshot-0.0.5.dist-info/LICENSE.txt
logshot-0.0.5.dist-info/METADATA
logshot-0.0.5.dist-info/WHEEL
logshot-0.0.5.dist-info/top_level.txt
logshot-0.0.5.dist-info/RECORD
