Metadata-Version: 2.1
Name: logshot
Version: 0.0.5
Summary: Simplified log tool that allows an easy manageable global logger
Home-page: https://github.com/pgmesa-packages/logshot
Author: Pablo García Mesa
Author-email: pgmesa.sm@gmail.com
License: UNKNOWN
Platform: UNKNOWN
Classifier: Programming Language :: Python :: 3.7
Classifier: License :: OSI Approved :: MIT License
Classifier: Operating System :: OS Independent
Requires-Python: >=3.7
License-File: LICENSE.txt
